aipkgs_socketio/__init__.py
aipkgs_socketio/core.py
aipkgs_socketio/helpers.py
aipkgs_socketio-1.0.1.dist-info/LICENSE.md
aipkgs_socketio-1.0.1.dist-info/METADATA
aipkgs_socketio-1.0.1.dist-info/WHEEL
aipkgs_socketio-1.0.1.dist-info/RECORD
